lint_utils/__init__.py
lint_utils/__main__.py
lint_utils/config.py
lint_utils/py.typed
lint_utils/regex.py
lint_utils/rules.py
lint_utils/tree_info.py
lint_utils/_cli_commands/__init__.py
lint_utils/_cli_commands/abc_.py
lint_utils/_cli_commands/check.py
lint_utils/_cli_commands/dto.py
lint_utils/_cli_commands/remind_later.py
lint_utils/common/__init__.py
lint_utils/common/files.py
lint_utils/common/std.py
lint_utils/common/text_styling.py
lint_utils/common/timer.py
lint_utils/visitors/__init__.py
lint_utils/visitors/base.py
lint_utils/visitors/dto.py
lint_utils/visitors/useless_fields.py
lint_utils-0.2.1.dist-info/METADATA
lint_utils-0.2.1.dist-info/WHEEL
lint_utils-0.2.1.dist-info/entry_points.txt
lint_utils-0.2.1.dist-info/licenses/LICENSE
lint_utils-0.2.1.dist-info/RECORD
