Metadata-Version: 2.4
Name: lint-utils
Version: 0.2.1
Summary: The humble linter package
Project-URL: GitHub, https://github.com/barbarrista/lint-utils
Author-email: Nikitosio Noskovinni <nik.noskov08@gmail.com>
License: MIT
License-File: LICENSE
Requires-Python: >=3.11
Requires-Dist: click>=8.1.8
Requires-Dist: msgspec>=0.19.0
Requires-Dist: toml>=0.10.2
